setup.py
jehhadwru13lvu3/__init__.py
jehhadwru13lvu3/one.py
jehhadwru13lvu3/two.py
jehhadwru13lvu3.egg-info/PKG-INFO
jehhadwru13lvu3.egg-info/SOURCES.txt
jehhadwru13lvu3.egg-info/dependency_links.txt
jehhadwru13lvu3.egg-info/top_level.txt