Metadata-Version: 2.1
Name: jehhadwru13lvu3
Version: 0.0.1
Summary: My Package Jehhadwru13lvu3
Author: Letton`
Author-email: letton@letton.com
